[
    {
    "pargarph":{
        "firstLine":"We commission the world’s most renowned course architects to",
      "secondLine":"design spectacular golf experiences on challenging yet ",
      "thirdLine":"incredibly playable 18-hole courses. Our trademark comfort ",
      "fourthLine":"stations also set new standards in on-course amenities."
    },
    "pargraphTwo":{
        "firstLine":"Our widely-acclaimed courses have been designed by",
      "secondLine":"some of the world’s very best architects, including ",
      "thirdLine":"Robert Trent Jones Jr. and Tom Fazio. "
    },
    "pargraphThree":{
        "firstLine":"And it’s their genius way of transforming unique",
      "secondLine":"landscapes into stunningly scenic courses that make ",
      "thirdLine":"our golf experience as beautiful as it is playable. "
    }

    
}
]